Metadata-Version: 1.1
Name: herald-slack
Version: 0.2
Summary: attr: herald_slack.__doc__
Home-page: https://github.com/cloudspectatordevelopment/herald-slack
Author: Anthony Monthe (ZuluPro)
Author-email: anthony.monthe@gmail.com
License: UNKNOWN
Keywords: notifications,slack
Platform: UNKNOWN
Classifier: Development Status :: 4 - Beta
Classifier: Intended Audience :: Developers
Classifier: License :: OSI Approved :: BSD License
Classifier: Operating System :: OS Independent
Classifier: Programming Language :: Python
Classifier: Programming Language :: Python :: 3
Classifier: Framework :: Django
Classifier: Topic :: Software Development
Classifier: Topic :: Communications :: Chat
